pkgver/__init__.py
scora/__init__.py
scora/commands/__init__.py
scora/commands/blocks/__init__.py
scora/commands/blocks/blocks.py
scora/commands/blocks/impl.py
scora/commands/flow/__init__.py
scora/commands/flow/flow.py
scora/commands/flow/impl.py
scora/helpers/__init__.py
scora/helpers/aws.py
scora/helpers/ecs_constants.py
scora/helpers/misc.py
scora/helpers/terminal.py
scora/models/__init__.py
scora/models/blocks/__init__.py
scora/models/blocks/blocks_config.py
scora/models/blocks/param.py
scora/models/blocks/project_config.py
scora/models/blocks/resource_config.py
scora_cli-1.7.0.dist-info/METADATA
scora_cli-1.7.0.dist-info/WHEEL
scora_cli-1.7.0.dist-info/entry_points.txt
scora_cli-1.7.0.dist-info/top_level.txt
scora_cli-1.7.0.dist-info/zip-safe
scora_cli-1.7.0.dist-info/RECORD
