Metadata-Version: 2.1
Name: scora-cli
Version: 1.7.0
Summary: Scora Platform CLI
Home-page: https://pypi.org/project/scora/
Author: Oncase
Author-email: contato@oncase.com.br
Keywords: scora
Classifier: Intended Audience :: Developers
Classifier: Natural Language :: English
Classifier: Programming Language :: Python :: 3.6
Requires-Dist: click (>=6.0)
Requires-Dist: twine
Requires-Dist: boto3
Requires-Dist: PyYAML (==5.3.1)
Requires-Dist: docker
Requires-Dist: cookiecutter
Provides-Extra: dev
Requires-Dist: twine (>=3.1.1) ; extra == 'dev'
Requires-Dist: Sphinx (==3.1.1) ; extra == 'dev'
Requires-Dist: sphinxcontrib-napoleon (==0.7) ; extra == 'dev'
Requires-Dist: sphinx-rtd-theme (==0.5.0) ; extra == 'dev'
Requires-Dist: sphinx-click (==2.3.2) ; extra == 'dev'
Requires-Dist: flake8 (==3.8.3) ; extra == 'dev'
